aiger_discrete/__init__.py
aiger_discrete/discrete.py
aiger_discrete/mdd.py
py_aiger_discrete-0.1.10.dist-info/LICENSE
py_aiger_discrete-0.1.10.dist-info/WHEEL
py_aiger_discrete-0.1.10.dist-info/METADATA
py_aiger_discrete-0.1.10.dist-info/RECORD
