Metadata-Version: 2.1
Name: py-aiger-discrete
Version: 0.1.10
Summary: Library for modeling functions over discrete sets using aiger circuits.
Home-page: https://github.com/mvcisback/py-aiger-discrete
License: MIT
Author: Marcell Vazquez-Chanlatte
Author-email: mvc@linux.com
Requires-Python: >=3.9,<4.0
Classifier: License :: OSI Approved :: MIT License
Classifier: Programming Language :: Python :: 3
Classifier: Programming Language :: Python :: 3.10
Classifier: Programming Language :: Python :: 3.9
Provides-Extra: mdd
Requires-Dist: funcy (>=1.14,<2.0)
Requires-Dist: mdd (>=0.3.3,<0.4.0); extra == "mdd"
Requires-Dist: py-aiger-bv (>=4.5.1,<5.0.0)
Requires-Dist: py-aiger-ptltl (>=3.0.1,<4.0.0)
Requires-Dist: pyrsistent (>=0.19,<0.20)
Project-URL: Repository, https://github.com/mvcisback/py-aiger-discrete
